gpluscodepy/__init__.py
gpluscodepy/gpluscodepy.py
gpluscodepy-0.0.1.dist-info/LICENSE
gpluscodepy-0.0.1.dist-info/METADATA
gpluscodepy-0.0.1.dist-info/WHEEL
gpluscodepy-0.0.1.dist-info/top_level.txt
gpluscodepy-0.0.1.dist-info/RECORD
