Metadata-Version: 2.1
Name: gpluscodepy
Version: 0.0.1
Summary: Simple plus code to lat/long decoder written for White Flag Project
Home-page: https://github.com/pervertedpokepuffs/gpluscodepy
Author: AHMAD AMIRUL ADLI BIN MAT ALI
Author-email: aaadlima97@gmail.com
License: UNKNOWN
Project-URL: Bug Tracker, https://github.com/pervertedpokepuffs/gpluscodepy/issues
Platform: UNKNOWN
Classifier: Programming Language :: Python :: 3
Classifier: License :: OSI Approved :: MIT License
Classifier: Operating System :: OS Independent
Requires-Python: >=3.6
License-File: LICENSE
